{"data":{"mongodbDatabaseArticles":{"id":"5b9248e987be056953db7c10","content":"<blockquote><p>Great bit by <a href=\"http://news.ycombinator.com/user?id=tsunamifury\">tsunamifury</a> on Hacker News:</p><p>Most people fail, most projects go unfinished, most beyond that never make enough money to sustain a company.</p> <p>A successful product is the evolutionary result of 10,000 products before it that failed, went unfinished, or were unprofitable. Even the best of the Valley didn't sit down, bang out some brilliant code, slap a business strategy on top, then cash a billion dollar check. They worked long and hard through repeated failures, with sometimes B and C squad talent, slowly carving away at the block of ideas until a product appeared. Then after that, they spend months or years compiling a business strategy and altering the product to become palatable to enough customers to gain a profit.</p> <p>It takes a team of imperfect people and a lot of time to make even a passable product. Even finishing a unprofitable product is an massive achievement in itself.</p></blockquote> ","title":"Why overnight success is a myth"}},"pageContext":{"id":"5b9248e987be056953db7c10"}}